csv_ingestor.py
csv_ingestor-0.1.3.dist-info/LICENSE.txt
csv_ingestor-0.1.3.dist-info/METADATA
csv_ingestor-0.1.3.dist-info/WHEEL
csv_ingestor-0.1.3.dist-info/top_level.txt
csv_ingestor-0.1.3.dist-info/RECORD
