Metadata-Version: 2.1
Name: csv-ingestor
Version: 0.1.3
Summary: Load data from CSV files into database tables
Author-email: Nic Wolff <nwolff@hearst.com>
License: MIT
Project-URL: Homepage, https://github.com/Media-Platforms/csv-ingestor
Project-URL: Changelog, https://github.com/Media-Platforms/csv-ingestor/releases
Requires-Python: >=3.10
License-File: LICENSE.txt
Requires-Dist: boto3
Requires-Dist: sqlalchemy
